[{"BANK":"THE NASIK MERCHANTS COOPERATIVE BANK LIMITED","ADDRESS":"DHANVARDHINI ,TILAK PATH, OPP. NEHARU GARDEN, NASHIK 422001","BRANCH":"DHANVARDHINI","CITY1":"NASHIK","CITY2":"NASIK","IFSC":"NMCB0000002","PHONE":"2308217","STATE":"MAHARASHTRA","STD_CODE":"253","bank_id":191},{"BANK":"THE NASIK MERCHANTS COOPERATIVE BANK LIMITED","ADDRESS":"430/11 ,  SHRIRAMWADI, M.G.ROAD,  NASHIK 422001","BRANCH":"MORNING  EVENING","CITY1":"NASHIK","CITY2":"NASIK","IFSC":"NMCB0000003","PHONE":"2308221","STATE":"MAHARASHTRA","STD_CODE":"253","bank_id":191},{"BANK":"THE NASIK MERCHANTS COOPERATIVE BANK LIMITED","ADDRESS":"A/16, M.I.D.C. AREA, PADMSHREE BABUBHAI RATHI CHOWK,SATPUR,  NASHIK  422007","BRANCH":"SATPUR (I.E.)","CITY1":"NASHIK","CITY2":"NASIK","IFSC":"NMCB0000004","PHONE":"2308223","STATE":"MAHARASHTRA","STD_CODE":"253","bank_id":191},{"BANK":"THE NASIK MERCHANTS COOPERATIVE BANK LIMITED","ADDRESS":"KRISHNAJI JOSHI COMPLEX, NEAR PANCHAVATI KARANJA,PANCHAVATI, NASHIK  422003","BRANCH":"PANCHAWATI","CITY1":"NASHIK","CITY2":"NASIK","IFSC":"NMCB0000005","PHONE":"2512996","STATE":"MAHARASHTRA","STD_CODE":"253","bank_id":191},{"BANK":"THE NASIK MERCHANTS COOPERATIVE BANK LIMITED","ADDRESS":"L-3, G-3, SUYOJIT TRADE CENTRE, OPP. RAJIV GANDHI BHAVAN,SHARANPUR ROAD, NASHIK 422002","BRANCH":"TILAKWADI","CITY1":"NASHIK","CITY2":"NASIK","IFSC":"NMCB0000006","PHONE":"2308224","STATE":"MAHARASHTRA","STD_CODE":"253","bank_id":191},{"BANK":"THE NASIK MERCHANTS COOPERATIVE BANK LIMITED","ADDRESS":"BHADRAKALI MANDIR, BHADRAKALI ROAD, NASHIK 422001","BRANCH":"BHADRAKALI","CITY1":"NASHIK","CITY2":"NASIK","IFSC":"NMCB0000007","PHONE":"2308226","STATE":"MAHARASHTRA","STD_CODE":"253","bank_id":191},{"BANK":"THE NASIK MERCHANTS COOPERATIVE BANK LIMITED","ADDRESS":"DHANLAXMI,  A/P. SAYKHEDA, TAL.NIPHAD, DIST.- NASHIK 422210","BRANCH":"SAYKHEDA","CITY1":"SAIKHEDA","CITY2":"NASIK","IFSC":"NMCB0000008","PHONE":"232074","STATE":"MAHARASHTRA","STD_CODE":"2550","bank_id":191},{"BANK":"THE NASIK MERCHANTS COOPERATIVE BANK LIMITED","ADDRESS":"19 & 20., SHOPPING CENTRE, GANDHINAGAR, NASHIK 422006","BRANCH":"GANDHINAGAR","CITY1":"NASHIK","CITY2":"NASIK","IFSC":"NMCB0000009","PHONE":"2414311","STATE":"MAHARASHTRA","STD_CODE":"253","bank_id":191},{"BANK":"THE NASIK MERCHANTS COOPERATIVE BANK LIMITED","ADDRESS":"SANT NIWAS, LATE MURLIDHAR PAWAR  CHOWK,  PATIL LANE,PRIYADARSHANI INDIRA GANHI PATH, A/P TRIMBAKESHWAR DIST - NASHIK  422212","BRANCH":"TRIMBAKESHWAR","CITY1":"TRIMBAK","CITY2":"NASIK","IFSC":"NMCB0000010","PHONE":"233155","STATE":"MAHARASHTRA","STD_CODE":"2594","bank_id":191},{"BANK":"THE NASIK MERCHANTS COOPERATIVE BANK LIMITED","ADDRESS":"SHOPPING CENTRE,CIDCO AREA,  SHIVAJI CHOWK, OLD CIDCO, NASHIK 422009","BRANCH":"CIDCO","CITY1":"NASHIK","CITY2":"NASIK","IFSC":"NMCB0000011","PHONE":"2392319","STATE":"MAHARASHTRA","STD_CODE":"253","bank_id":191},{"BANK":"THE NASIK MERCHANTS COOPERATIVE BANK LIMITED","ADDRESS":"HOTEL RAVINDRA COMPLEX, DWARAKA CORNER, NASHIK-POONA ROAD, NASHIK  422001","BRANCH":"POONA ROAD","CITY1":"NASHIK","CITY2":"NASIK","IFSC":"NMCB0000012","PHONE":"2308228","STATE":"MAHARASHTRA","STD_CODE":"253","bank_id":191},{"BANK":"THE NASIK MERCHANTS COOPERATIVE BANK LIMITED","ADDRESS":"VIMAL PARK,  NEAR MAMAMUNGI MANGAL KARYALAY, PUMPING STATION ROAD, NEAR MAMA MUNGI MANGAL KARYALAY,GANGAPUR ROAD, NASHIK  422013","BRANCH":"GANGAPUR ROAD","CITY1":"NASHIK","CITY2":"NASIK","IFSC":"NMCB0000013","PHONE":"2308229","STATE":"MAHARASHTRA","STD_CODE":"253","bank_id":191},{"BANK":"THE NASIK MERCHANTS COOPERATIVE BANK LIMITED","ADDRESS":"DHANASHRI ,  P/4, M.I.D.C. , AMBAD, NASHIK 422010","BRANCH":"AMBAD (I.E.)","CITY1":"NASHIK","CITY2":"NASIK","IFSC":"NMCB0000014","PHONE":"2308230","STATE":"MAHARASHTRA","STD_CODE":"253","bank_id":191},{"BANK":"THE NASIK MERCHANTS COOPERATIVE BANK LIMITED","ADDRESS":"AGRASEN BHAVAN VISHWASTA TRUST, NEAR SUNDAR NARAYAN MANDIR, NASHIK  422001","BRANCH":"RAVIWAR PETH","CITY1":"NASHIK","CITY2":"NASIK","IFSC":"NMCB0000015","PHONE":"2308231","STATE":"MAHARASHTRA","STD_CODE":"253","bank_id":191},{"BANK":"THE NASIK MERCHANTS COOPERATIVE BANK LIMITED","ADDRESS":"CHANDWADKAR SADAN,  WARACHI PETH, A/P & TAL - IGATPURI, DIST.- NASHIK  422403","BRANCH":"IGATPURI","CITY1":"IGATPURI","CITY2":"NASIK","IFSC":"NMCB0000016","PHONE":"244238","STATE":"MAHARASHTRA","STD_CODE":"2553","bank_id":191},{"BANK":"THE NASIK MERCHANTS COOPERATIVE BANK LIMITED","ADDRESS":"S/942, ASHADH SECTOR,  RAJRATNA NAGAR, PAWAN NAGAR, NASHIK  422009","BRANCH":"PAWAN NAGAR","CITY1":"NASHIK","CITY2":"NASIK","IFSC":"NMCB0000017","PHONE":"2393793","STATE":"MAHARASHTRA","STD_CODE":"253","bank_id":191},{"BANK":"THE NASIK MERCHANTS COOPERATIVE BANK LIMITED","ADDRESS":"26 TO 31, SANAP COMPLEX,  MALEGAON  MANMAD ROAD, A/P MANMAD, TAL- NANDGAON, DIST - NASHIK  423104","BRANCH":"MANMAD","CITY1":"MANMAD","CITY2":"NASIK","IFSC":"NMCB0000018","PHONE":"222610","STATE":"MAHARASHTRA","STD_CODE":"2591","bank_id":191},{"BANK":"THE NASIK MERCHANTS COOPERATIVE BANK LIMITED","ADDRESS":"723, PETH GALLI, A/P NAMPUR, TAL- SATANA , DIST - NASHIK  423204","BRANCH":"NAMPUR","CITY1":"NAMPUR","CITY2":"NASIK","IFSC":"NMCB0000019","PHONE":"234294","STATE":"MAHARASHTRA","STD_CODE":"2555","bank_id":191},{"BANK":"THE NASIK MERCHANTS COOPERATIVE BANK LIMITED","ADDRESS":"MAIN ROAD, A/P. UMARANE, TAL.- MALEGAON, DIST.-NASHIK  423110","BRANCH":"UMRANE","CITY1":"UMARANE","CITY2":"NASIK","IFSC":"NMCB0000020","PHONE":"264469","STATE":"MAHARASHTRA","STD_CODE":"2598","bank_id":191},{"BANK":"THE NASIK MERCHANTS COOPERATIVE BANK LIMITED","ADDRESS":"LAXMI-NARAYAN BUILDING, BAZAR PETH, A/P. VINCHUR, TAL-  NIPHAD,  DIST. NASHIK  422306","BRANCH":"VINCHUR","CITY1":"VINCHUR","CITY2":"NASIK","IFSC":"NMCB0000021","PHONE":"261155","STATE":"MAHARASHTRA","STD_CODE":"2550","bank_id":191},{"BANK":"THE NASIK MERCHANTS COOPERATIVE BANK LIMITED","ADDRESS":"A 3 TO 8, RADHAI SANKUL, OPP. MARKET YARD, KOTAMGAON ROAD, A/P LASALGAON, TAL-NIPHAD DIST.-NASHIK  422306","BRANCH":"LASALGAON","CITY1":"LASALGAON","CITY2":"NASIK","IFSC":"NMCB0000022","PHONE":"266942","STATE":"MAHARASHTRA","STD_CODE":"2550","bank_id":191},{"BANK":"THE NASIK MERCHANTS COOPERATIVE BANK LIMITED","ADDRESS":"201, FIRST FLOOR, BABA COMPLEX,  AGRA ROAD, A/P PIMPALGAON(B), TAL-NIPHAD, DIST-NASHIK 422209","BRANCH":"PIMPALGAON ( B )","CITY1":"PIMPALGAON","CITY2":"NASIK","IFSC":"NMCB0000023","PHONE":"251282","STATE":"MAHARASHTRA","STD_CODE":"2550","bank_id":191},{"BANK":"THE NASIK MERCHANTS COOPERATIVE BANK LIMITED","ADDRESS":"M.G. LODHA MARKET, SATANA ROAD, A/P. TAL. MALEGAON, DIST. NASHIK423203","BRANCH":"MALEGAON","CITY1":"MALEGAON","CITY2":"NASIK","IFSC":"NMCB0000024","PHONE":"251002","STATE":"MAHARASHTRA","STD_CODE":"2554","bank_id":191},{"BANK":"THE NASIK MERCHANTS COOPERATIVE BANK LIMITED","ADDRESS":"1793, ASHIRWAD BUILDING, NEHRU ROAD, A/P.TAL. SATANA,  DIST. NASHIK  423301","BRANCH":"SATANA","CITY1":"SATANA","CITY2":"NASIK","IFSC":"NMCB0000025","PHONE":"224015","STATE":"MAHARASHTRA","STD_CODE":"2555","bank_id":191},{"BANK":"THE NASIK MERCHANTS COOPERATIVE BANK LIMITED","ADDRESS":"SHOP NO-10&11, REGIMENTAL PLAZA, NEAR BITCO POINT, NASIK ROAD, NASHIK 422101","BRANCH":"NASIK ROAD","CITY1":"NASHIK","CITY2":"NASIK","IFSC":"NMCB0000026","PHONE":"2460160","STATE":"MAHARASHTRA","STD_CODE":"253","bank_id":191},{"BANK":"THE NASIK MERCHANTS COOPERATIVE BANK LIMITED","ADDRESS":"VIJAYRAJ MARKET,OLD MUMBAI AGRA ROAD, A/P GHOTI, TAL-IGATPURI, DIST - NASHIK  422402","BRANCH":"GHOTI","CITY1":"GHOTI","CITY2":"NASIK","IFSC":"NMCB0000027","PHONE":"220816","STATE":"MAHARASHTRA","STD_CODE":"2553","bank_id":191},{"BANK":"THE NASIK MERCHANTS COOPERATIVE BANK LIMITED","ADDRESS":"OPP. SHRIRAM SAW MILL, NEAR BUS STAND, A / P. TAL- KALVAN, DIST - NASHIK  423501","BRANCH":"KALWAN","CITY1":"KALVAN","CITY2":"NASIK","IFSC":"NMCB0000028","PHONE":"221739","STATE":"MAHARASHTRA","STD_CODE":"2592","bank_id":191},{"BANK":"THE NASIK MERCHANTS COOPERATIVE BANK LIMITED","ADDRESS":"SANDESH  SANKUL CO.OP. HSG. SOC.,  OPP. RAJSARATHI SOC., INDIRANAGAR, NASHIK  422009","BRANCH":"INDIRANAGAR","CITY1":"NASHIK","CITY2":"NASIK","IFSC":"NMCB0000029","PHONE":"2325793","STATE":"MAHARASHTRA","STD_CODE":"253","bank_id":191},{"BANK":"THE NASIK MERCHANTS COOPERATIVE BANK LIMITED","ADDRESS":"NAGARPARISHAD SANKUL, NEAR S.T. STAND, A/P TAL- SINNAR DIST - NASHIK  422103","BRANCH":"SINNAR","CITY1":"SINNAR","CITY2":"NASIK","IFSC":"NMCB0000030","PHONE":"222084","STATE":"MAHARASHTRA","STD_CODE":"2551","bank_id":191},{"BANK":"THE NASIK MERCHANTS COOPERATIVE BANK LIMITED","ADDRESS":"6 TO 10, JANAKI SANKUL,  OLD KALWAN ROAD, A/P TAL- DINDORI, DIST - NASHIK  422202","BRANCH":"DINDORI","CITY1":"DINDORI","CITY2":"NASIK","IFSC":"NMCB0000031","PHONE":"221402","STATE":"MAHARASHTRA","STD_CODE":"2557","bank_id":191},{"BANK":"THE NASIK MERCHANTS COOPERATIVE BANK LIMITED","ADDRESS":"H.NO. 1/24/30 & 31, GROUND FLOOR, SADAR BAZAR, SHOLA CHOWK, JALNA DIST.- JALANA  431203","BRANCH":"JALANA","CITY1":"JALNA","CITY2":"JALNA","IFSC":"NMCB0000032","PHONE":"236107","STATE":"MAHARASHTRA","STD_CODE":"2482","bank_id":191},{"BANK":"THE NASIK MERCHANTS COOPERATIVE BANK LIMITED","ADDRESS":"C.S.NO-1089, NEAR DATTA MANDIR, 1ST FLOOR, SWAMI SAHAWAS,  SHIVAJI ROAD, BUDHAWAR PETH,PUNE DIST.- PUNE 411002","BRANCH":"PUNE","CITY1":"PUNE","CITY2":"PUNE","IFSC":"NMCB0000033","PHONE":"24484003","STATE":"MAHARASHTRA","STD_CODE":"20","bank_id":191},{"BANK":"THE NASIK MERCHANTS COOPERATIVE BANK LIMITED","ADDRESS":"PLOT NO 50, BISANJI NAGAR, ZILHA PETH, NEAR HOME GUARD OFFICE, JALGAON, DIST.- JALGAON  425001","BRANCH":"JALGAON","CITY1":"JALGAON","CITY2":"JALGAON","IFSC":"NMCB0000034","PHONE":"2221364","STATE":"MAHARASHTRA","STD_CODE":"257","bank_id":191},{"BANK":"THE NASIK MERCHANTS COOPERATIVE BANK LIMITED","ADDRESS":"2424, FIRST FLOOR,  DAL MANDAI, AHMADNAGAR , DIST.- AHMADNAGAR 414001","BRANCH":"AHMEDNAGAR","CITY1":"AHMADNAGAR","CITY2":"AHMADNAGAR","IFSC":"NMCB0000035","PHONE":"2354262","STATE":"MAHARASHTRA","STD_CODE":"241","bank_id":191},{"BANK":"THE NASIK MERCHANTS COOPERATIVE BANK LIMITED","ADDRESS":"RAJGIR COURT, WING-B, GROUND FLOOR, KOHINOOR ROAD,OPP.HOTEL PRITAM, DADAR (E), DIST.-MUMBAI 400014","BRANCH":"DADAR","CITY1":"MUMBAI","CITY2":"G. BOMBAY","IFSC":"NMCB0000036","PHONE":"24155106","STATE":"MAHARASHTRA","STD_CODE":"22","bank_id":191},{"BANK":"THE NASIK MERCHANTS COOPERATIVE BANK LIMITED","ADDRESS":"108, M. C. D.JAIN DHARMARH MEDICAL , BHAGWAN MAHAVIR MARG, A /P.TAL.-NANDGAON, DIST - NASHIK  423106","BRANCH":"NANDGAON","CITY1":"NANDGAON","CITY2":"NASIK","IFSC":"NMCB0000037","PHONE":"242516","STATE":"MAHARASHTRA","STD_CODE":"2552","bank_id":191},{"BANK":"THE NASIK MERCHANTS COOPERATIVE BANK LIMITED","ADDRESS":"COMMERCIAL COMPLEX NO 2, SHOP NO-15, MARKET YARD,  PETH ROAD, PANCHAVATI, NASHIK 422003","BRANCH":"ADGAON NAKA","CITY1":"NASHIK","CITY2":"NASIK","IFSC":"NMCB0000038","PHONE":"2022993","STATE":"MAHARASHTRA","STD_CODE":"253","bank_id":191},{"BANK":"THE NASIK MERCHANTS COOPERATIVE BANK LIMITED","ADDRESS":"106,PANCHAL LANE, S.S.JAIN MURTIPUJAK SANGHA A/P VANI , TAL-DINDORI, DIST.-NASHIK  422215","BRANCH":"VANI","CITY1":"VANI","CITY2":"NASIK","IFSC":"NMCB0000039","PHONE":"220700","STATE":"MAHARASHTRA","STD_CODE":"2557","bank_id":191},{"BANK":"THE NASIK MERCHANTS COOPERATIVE BANK LIMITED","ADDRESS":"DUNGERWAL SANKUL, SOMWAR PETH, A/P.TAL.-CHANDWAD,  DIST.-NASHIK  423101","BRANCH":"CHANDVAD","CITY1":"CHANDVAD","CITY2":"NASIK","IFSC":"NMCB0000040","PHONE":"253218","STATE":"MAHARASHTRA","STD_CODE":"2556","bank_id":191},{"BANK":"THE NASIK MERCHANTS COOPERATIVE BANK LIMITED","ADDRESS":"FIRST FLOOR, AMARNATH AVENUE ,GAULIGUDA CHAMAN, HYDERABAD DIST-HYDERABAD (A.P.) 500012","BRANCH":"HYDERABAD","CITY1":"HYDERABAD","CITY2":"HYDERABAD","IFSC":"NMCB0000041","PHONE":"24734029","STATE":"ANDHRA PRADESH","STD_CODE":"40","bank_id":191},{"BANK":"THE NASIK MERCHANTS COOPERATIVE BANK LIMITED","ADDRESS":"SHIVAJI ROAD, SHRIRAMPUR, A/P SHRIRAMPUR,  DIST -AHMEDNAGAR 413709","BRANCH":"SHRIRAMPUR","CITY1":"SHRIRAMPUR","CITY2":"AHMADNAGAR","IFSC":"NMCB0000042","PHONE":"222650","STATE":"MAHARASHTRA","STD_CODE":"2422","bank_id":191},{"BANK":"THE NASIK MERCHANTS COOPERATIVE BANK LIMITED","ADDRESS":"10&11, 2ND FLOOR, MAHATMA PHULE AND  DR AMBEDAKAR SHOPPING CENTER, A/P RAHATA, DIST.-AHMADNAGAR 423107","BRANCH":"RAHATA","CITY1":"RAHATA","CITY2":"AHMADNAGAR","IFSC":"NMCB0000043","PHONE":"243656","STATE":"MAHARASHTRA","STD_CODE":"2423","bank_id":191},{"BANK":"THE NASIK MERCHANTS COOPERATIVE BANK LIMITED","ADDRESS":"C.S.NO 868, TP 6, FP 264/P , SHRI JAI MARUTI COMPLEX,UDHANA DARWAJA, RING ROAD,NEAR GUJRAT SAMACHAR PRESS, SURAT DIST.-SURAT (GUJARAT) 395002","BRANCH":"SURAT","CITY1":"SURAT","CITY2":"SURAT","IFSC":"NMCB0000044","PHONE":"2631670","STATE":"GUJARAT","STD_CODE":"261","bank_id":191},{"BANK":"THE NASIK MERCHANTS COOPERATIVE BANK LIMITED","ADDRESS":"2 TO 5, BHAVANA SANKUL ,  OPP.ASHOKA TOWER, ASHOKA MARG, NASHIK 422006","BRANCH":"ASHOKAMARG","CITY1":"NASHIK","CITY2":"NASIK","IFSC":"NMCB0000045","PHONE":"2025083","STATE":"MAHARASHTRA","STD_CODE":"253","bank_id":191},{"BANK":"THE NASIK MERCHANTS COOPERATIVE BANK LIMITED","ADDRESS":"SHRI KALASHAKTI APPT.,BHABHA NAGAR, MUMBAI NAKA, NASHIK 422011","BRANCH":"MUMBAINAKA","CITY1":"NASHIK","CITY2":"NASIK","IFSC":"NMCB0000046","PHONE":"2501938","STATE":"MAHARASHTRA","STD_CODE":"253","bank_id":191},{"BANK":"THE NASIK MERCHANTS COOPERATIVE BANK LIMITED","ADDRESS":"GAYATRI SOC., NEW NAGAR ROAD, A/P. TAL- SANGAMNER ,  DIST.-AHMADNAGAR 422605","BRANCH":"SANGAMNER","CITY1":"SANGAMNER","CITY2":"AHMADNAGAR","IFSC":"NMCB0000047","PHONE":"222191","STATE":"MAHARASHTRA","STD_CODE":"2425","bank_id":191},{"BANK":"THE NASIK MERCHANTS COOPERATIVE BANK LIMITED","ADDRESS":"3076, BAGWANPURA ,  OLD NASHIK, NASHIK 422001","BRANCH":"OLD NASHIK","CITY1":"NASHIK","CITY2":"NASIK","IFSC":"NMCB0000048","PHONE":"2595811","STATE":"MAHARASHTRA","STD_CODE":"253","bank_id":191},{"BANK":"THE NASIK MERCHANTS COOPERATIVE BANK LIMITED","ADDRESS":"1ST FLOOR, JADHAV COMPLEX, OPP VISHWA SATYA COLLEGE, A/P OJHAR, TAL-NIPHAD, DIST.-NASHIK  422206","BRANCH":"OJHAR","CITY1":"OJHAR","CITY2":"NASIK","IFSC":"NMCB0000049","PHONE":"271271","STATE":"MAHARASHTRA","STD_CODE":"2550","bank_id":191},{"BANK":"THE NASIK MERCHANTS COOPERATIVE BANK LIMITED","ADDRESS":"212 , OLD HEGADEWAR HOPITAL ROAD. SAMARTH NAGAR. OPP, STATE BANK OF HYDERBAD. AURANGABAD, 431 001","BRANCH":"AURANGABAD","CITY1":"AURANGABAD","CITY2":"AURANGABAD","IFSC":"NMCB0000050","PHONE":"2340729","STATE":"MAHARASHTRA","STD_CODE":"240","bank_id":191},{"BANK":"THE NASIK MERCHANTS COOPERATIVE BANK LIMITED","ADDRESS":"51, TELI VARG SAMAJ MANGAL KARYALAY, MAIN ROAD, A /P. GIRNARE DIST.-NASHIK  422203","BRANCH":"GIRNARE","CITY1":"GIRNARE","CITY2":"NASIK","IFSC":"NMCB0000051","PHONE":"2215603","STATE":"MAHARASHTRA","STD_CODE":"253","bank_id":191},{"BANK":"THE NASIK MERCHANTS COOPERATIVE BANK LIMITED","ADDRESS":"278 / 1 / 2, RUNWAL PLAZA ,  SHANI CHOWK, A/P. TAL- NIPHAD, DIST. NASHIK 422303","BRANCH":"NIPHAD","CITY1":"NIPHAD","CITY2":"NASIK","IFSC":"NMCB0000052","PHONE":"242006","STATE":"MAHARASHTRA","STD_CODE":"2550","bank_id":191},{"BANK":"THE NASIK MERCHANTS COOPERATIVE BANK LIMITED","ADDRESS":"2139, HUNDIWALA ROAD,  NEAR RANA PRATAP PUTALA, A/P.TAL- YEOLA DIST.-NASHIK  423401","BRANCH":"YEOLA","CITY1":"YEOLA","CITY2":"NASIK","IFSC":"NMCB0000053","PHONE":"267008","STATE":"MAHARASHTRA","STD_CODE":"2559","bank_id":191},{"BANK":"THE NASIK MERCHANTS COOPERATIVE BANK LIMITED","ADDRESS":"82, NAGESH BHAVAN,  HAOUSAN ROAD, A/P. DEOLALI CAMP,  DIST.-NASHIK  422401","BRANCH":"DEOLALI CAMP","CITY1":"DEOLALI","CITY2":"NASIK","IFSC":"NMCB0000054","PHONE":"2492525","STATE":"MAHARASHTRA","STD_CODE":"253","bank_id":191},{"BANK":"THE NASIK MERCHANTS COOPERATIVE BANK LIMITED","ADDRESS":"1,2,3 ANMOL PRIDE, CHOWK-2, GOVIND NAGAR, NASHIK 422009","BRANCH":"GOVINDNAGAR","CITY1":"NASHIK","CITY2":"NASIK","IFSC":"NMCB0000055","PHONE":"2471130","STATE":"MAHARASHTRA","STD_CODE":"253","bank_id":191},{"BANK":"THE NASIK MERCHANTS COOPERATIVE BANK LIMITED","ADDRESS":"HOUSE NO 24, OPP DENA BANK, A/P HARSUL TAL.TRAMBAKESHWAR  NASHIK 422204","BRANCH":"HARSUL","CITY1":"HARSUL","CITY2":"NASIK","IFSC":"NMCB0000056","PHONE":"257555","STATE":"MAHARASHTRA","STD_CODE":"2558","bank_id":191},{"BANK":"THE NASIK MERCHANTS COOPERATIVE BANK LIMITED","ADDRESS":"A-9 RAJDEEP BUILDING ,STATE EMPLOYEE SOCIETY, ASHOK NAGAR  SATPUR  NASHIK 422012","BRANCH":"ASHOK NAGAR","CITY1":"NASHIK","CITY2":"NASIK","IFSC":"NMCB0000057","PHONE":"2351921","STATE":"MAHARASHTRA","STD_CODE":"253","bank_id":191},{"BANK":"THE NASIK MERCHANTS COOPERATIVE BANK LIMITED","ADDRESS":"631-SANTA DNYANESHWAR NAGAR ,JAILROAD  DASAK  NASHIK ROAD , NASHIK 422101","BRANCH":"JAIL ROAD","CITY1":"NASHIK","CITY2":"NASIK","IFSC":"NMCB0000058","PHONE":"2431966","STATE":"MAHARASHTRA","STD_CODE":"253","bank_id":191},{"BANK":"THE NASIK MERCHANTS COOPERATIVE BANK LIMITED","ADDRESS":"HOUSE N.70, BAJAR PETH,NEAR NDCC BANK A/P SURGANA NASHIK","BRANCH":"SURGANA","CITY1":"SURGANA","CITY2":"NASIK","IFSC":"NMCB0000059","PHONE":"223258","STATE":"MAHARASHTRA","STD_CODE":"2593","bank_id":191},{"BANK":"THE NASIK MERCHANTS COOPERATIVE BANK LIMITED","ADDRESS":"GRAM PANCHAYAT MILKAT NO.1719, INDRAPRASTHA COMPLEX, SWARUP NAGAR, LASUR STATION, TAL. GANGAPUR DIST.-AURANGABAD 423702","BRANCH":"LASUR STATION","CITY1":"LASUR STATION","CITY2":"AURANGABAD","IFSC":"NMCB0000060","PHONE":"241059","STATE":"MAHARASHTRA","STD_CODE":"2433","bank_id":191},{"BANK":"THE NASIK MERCHANTS COOPERATIVE BANK LIMITED","ADDRESS":"WARDHAMAN  JAIN SHRAVAK SANGHA MARWADI GALLI, BHAGUR DIST NASHIK","BRANCH":"BHAGUR","CITY1":"NASHIK","CITY2":"NASIK","IFSC":"NMCB0000061","PHONE":"0","STATE":"MAHARASHTRA","STD_CODE":"0","bank_id":191},{"BANK":"THE NASIK MERCHANTS COOPERATIVE BANK LIMITED","ADDRESS":"YASHWANT GRAMIN BIGARSHETI PATSANSATHA BUILDING, NEAR STATE BANK OF INDIA, BAZAR PETH, PEITH, DIST NASHIK","BRANCH":"PEITH","CITY1":"NASHIK","CITY2":"NASIK","IFSC":"NMCB0000062","PHONE":"0","STATE":"MAHARASHTRA","STD_CODE":"0","bank_id":191},{"BANK":"THE NASIK MERCHANTS COOPERATIVE BANK LIMITED","ADDRESS":"SHARDA NIWAS, VISHWSINDHUNAGAR , AT POST DEOLA, DIST NASHIK","BRANCH":"DEOLA","CITY1":"DEOLA","CITY2":"NASIK","IFSC":"NMCB0000063","PHONE":"0","STATE":"MAHARASHTRA","STD_CODE":"0","bank_id":191},{"BANK":"THE NASIK MERCHANTS COOPERATIVE BANK LIMITED","ADDRESS":"JANAKI PLAZA, GOLE COLONY, NASHIK 422 004","BRANCH":"GOLE COLONY","CITY1":"NASHIK","CITY2":"NASIK","IFSC":"NMCB0000064","PHONE":"0","STATE":"MAHARASHTRA","STD_CODE":"0","bank_id":191},{"BANK":"THE NASIK MERCHANTS COOPERATIVE BANK LIMITED","ADDRESS":"K-30, APMC MARKET NO 1 VASHI NEW MUMBAI 400 703","BRANCH":"VASHI","CITY1":"VASHI","CITY2":"PUNE","IFSC":"NMCB0000065","PHONE":"0","STATE":"MAHARASHTRA","STD_CODE":"0","bank_id":191},{"BANK":"THE NASIK MERCHANTS COOPERATIVE BANK LIMITED","ADDRESS":"PRITHWIPRASTHA BUILDING, AT POST CHAKAN TAL KHED, DIST PUNE 420 501","BRANCH":"CHAKAN","CITY1":"CHAKAN","CITY2":"PUNE","IFSC":"NMCB0000066","PHONE":"0","STATE":"MAHARASHTRA","STD_CODE":"0","bank_id":191},{"BANK":"THE NASIK MERCHANTS COOPERATIVE BANK LIMITED","ADDRESS":"H. NO, 3036, NEAR PACH KANDIL,  SHERE PUNJAB HOTEL, MUMBAI AGRA ROAD, DHULE 424 001","BRANCH":"DHULE","CITY1":"DHULE","CITY2":"DHULE","IFSC":"NMCB0000067","PHONE":"0","STATE":"MAHARASHTRA","STD_CODE":"0","bank_id":191},{"BANK":"THE NASIK MERCHANTS COOPERATIVE BANK LIMITED","ADDRESS":"ANANDINAGAR SOCIETY, ANANDWALI, NASHIK 422 013","BRANCH":"ANANDWALI","CITY1":"NASHIK","CITY2":"NASIK","IFSC":"NMCB0000068","PHONE":"0","STATE":"MAHARASHTRA","STD_CODE":"0","bank_id":191},{"BANK":"THE NASIK MERCHANTS COOPERATIVE BANK LIMITED","ADDRESS":"NIMA HOUSE, MALEGAON SINNAR MIDC DIST NASHIK","BRANCH":"MALEGAON(SINNAR)","CITY1":"SINNAR","CITY2":"NASIK","IFSC":"NMCB0000069","PHONE":"0","STATE":"MAHARASHTRA","STD_CODE":"0","bank_id":191},{"BANK":"THE NASIK MERCHANTS COOPERATIVE BANK LIMITED","ADDRESS":"HAT DARVAJA, NEAR MAHATMA GANDHI STATUE, AT POST, TAL DIST,NANDURBAR","BRANCH":"NANDURBAR","CITY1":"NANDURBAR","CITY2":"NANDURBAR","IFSC":"NMCB0000070","PHONE":"0","STATE":"MAHARASHTRA","STD_CODE":"0","bank_id":191},{"BANK":"THE NASIK MERCHANTS COOPERATIVE BANK LIMITED","ADDRESS":"JAY GANGA BHUVAN, A/P DONDAICHA TAL SHINDKHEDA DIST, NANDURBAR","BRANCH":"DONDAICHA","CITY1":"DONDAICHA","CITY2":"NANDURBAR","IFSC":"NMCB0000071","PHONE":"0","STATE":"MAHARASHTRA","STD_CODE":"0","bank_id":191},{"BANK":"THE NASIK MERCHANTS COOPERATIVE BANK LIMITED","ADDRESS":"GAVHANE VASTI, SADASHIV PALACE, A/P BHOSARI DIST PUNE","BRANCH":"BHOSARI (PUNE)","CITY1":"BHOSARI","CITY2":"PUNE","IFSC":"NMCB0000072","PHONE":"0","STATE":"MAHARASHTRA","STD_CODE":"0","bank_id":191},{"BANK":"THE NASIK MERCHANTS COOPERATIVE BANK LIMITED","ADDRESS":"NEAR HOTEL SHIVA, DINDORI ROAD, MHASRUL, NASHIK","BRANCH":"MHASRUL","CITY1":"MHASRUL","CITY2":"NASIK","IFSC":"NMCB0000073","PHONE":"0","STATE":"MAHARASHTRA","STD_CODE":"0","bank_id":191},{"BANK":"THE NASIK MERCHANTS COOPERATIVE BANK LIMITED","ADDRESS":"N 53/ VE 12/8 SWAMI BUILDING, PATIL NAGAR UNTWADI NEW NASHIK 422 009","BRANCH":"UNTWADI(TRIMURTY)","CITY1":"NASHIK","CITY2":"NASIK","IFSC":"NMCB0000074","PHONE":"0","STATE":"MAHARASHTRA","STD_CODE":"0","bank_id":191},{"BANK":"THE NASIK MERCHANTS COOPERATIVE BANK LIMITED","ADDRESS":"MATHURA APPT. 1 ST FLOOR, NEAR BUS STOP. AT POST ADGAON  DIST NASHIK","BRANCH":"ADGAON","CITY1":"NASHIK","CITY2":"NASIK","IFSC":"NMCB0000075","PHONE":"0","STATE":"MAHARASHTRA","STD_CODE":"0","bank_id":191},{"BANK":"THE NASIK MERCHANTS COOPERATIVE BANK LIMITED","ADDRESS":"GONDE DUMALA MIDC MUMBAI AGRA ROAD NASHIK TAL IGATPURI DIST NASHIK","BRANCH":"GONDE DUMALA","CITY1":"NASHIK","CITY2":"NASIK","IFSC":"NMCB0000076","PHONE":"0","STATE":"MAHARASHTRA","STD_CODE":"0","bank_id":191},{"BANK":"THE NASIK MERCHANTS COOPERATIVE BANK LIMITED","ADDRESS":"AT POST CHANDORI, TAL DIST NASHIK","BRANCH":"CHANDORI","CITY1":"CHANDORI","CITY2":"NASIK","IFSC":"NMCB0000077","PHONE":"0","STATE":"MAHARASHTRA","STD_CODE":"0","bank_id":191},{"BANK":"THE NASIK MERCHANTS COOPERATIVE BANK LIMITED","ADDRESS":"SOHAM COMPLEX, PATIL LANE NO 3  & 4 COLLEGE ROAD , NASHIK","BRANCH":"COLLEGE ROAD","CITY1":"NASHIK","CITY2":"NASIK","IFSC":"NMCB0000078","PHONE":"0","STATE":"MAHARASHTRA","STD_CODE":"0","bank_id":191},{"BANK":"THE NASIK MERCHANTS COOPERATIVE BANK LIMITED","ADDRESS":"SHRIKRUSHNA HIGHTS GALA NO 1 TO 4 HANUMANWADI","BRANCH":"HANUMANWADI","CITY1":"NASHIK","CITY2":"NASIK","IFSC":"NMCB0000079","PHONE":"0","STATE":"MAHARASHTRA","STD_CODE":"0","bank_id":191},{"BANK":"THE NASIK MERCHANTS COOPERATIVE BANK LIMITED","ADDRESS":"S.R.NO 711 AT POST ABHONA TAL DIST NASHIK","BRANCH":"ABHONA","CITY1":"ABHONA","CITY2":"NASIK","IFSC":"NMCB0000080","PHONE":"0","STATE":"MAHARASHTRA","STD_CODE":"0","bank_id":191},{"BANK":"THE NASIK MERCHANTS COOPERATIVE BANK LIMITED","ADDRESS":"H.NO. 309/13/3 AT POST MAKHAMALABAD DIST NASHIK","BRANCH":"MAKHAMALABAD","CITY1":"NASHIK","CITY2":"NASIK","IFSC":"NMCB0000081","PHONE":"0","STATE":"MAHARASHTRA","STD_CODE":"0","bank_id":191}]